alchemize/__init__.py
alchemize/helpers.py
alchemize/mapping.py
alchemize/transmute.py
alchemize-0.14.0.data/data/LICENSE
alchemize-0.14.0.dist-info/LICENSE
alchemize-0.14.0.dist-info/METADATA
alchemize-0.14.0.dist-info/WHEEL
alchemize-0.14.0.dist-info/top_level.txt
alchemize-0.14.0.dist-info/RECORD
