Metadata-Version: 2.1
Name: alchemize
Version: 0.14.0
Summary: A simple library that allows for serialization and deserialization of models via mapping definitions
Home-page: https://github.com/jmvrbanac/alchemize
Author: John Vrbanac
Author-email: john.vrbanac@linux.com
License: Apache License 2.0
Keywords: model serialize deserialize transmute
Platform: UNKNOWN
Classifier: Development Status :: 3 - Alpha
Classifier: Intended Audience :: Developers
Classifier: License :: OSI Approved :: Apache Software License
Classifier: Programming Language :: Python :: 2.7
Classifier: Programming Language :: Python :: 3.4
Classifier: Programming Language :: Python :: 3.5
Classifier: Programming Language :: Python :: 3.6
Classifier: Programming Language :: Python :: Implementation :: PyPy
Classifier: Operating System :: POSIX :: Linux
Requires-Dist: six
